{
	"MoveHorizontal": {
		"InputType": "Analog",
		"Bindings": [
			{
				"Device": "Keyboard",
				"Input": "A",
				"Event": "Down",
				"Scale": -1.0
			},
			{
				"Device": "Keyboard",
				"Input": "D",
				"Event": "Down",
				"Scale": 1.0
			},
			{
				"Device": "Controller",
				"Input": "LeftStick",
				"Axis": "X",
				"Event": "Down"
			}
		]
	},
	"MoveVertical": {
		"InputType": "Analog",
		"Bindings": [
			{
				"Device": "Keyboard",
				"Input": "W",
				"Event": "Down",
				"Scale": 1.0
			},
			{
				"Device": "Keyboard",
				"Input": "S",
				"Event": "Down",
				"Scale": -1.0
			},
			{
				"Device": "Controller",
				"Input": "LeftStick",
				"Axis": "Y",
				"Event": "Down"
			}
		]
	},
	"BulletFire": {
		"InputType": "Digital",
		"Bindings": [
			{
				"Device": "Keyboard",
				"Input": "Space",
				"Event": "Down"
			},
			{
				"Device": "Keyboard",
				"Input": "Enter",
				"Event": "Down"
			},
			{
				"Device": "Controller",
				"Input": "ButtonA",
				"Event": "Down"
			}
		]
	},
	"BulletChangePrev": {
		"InputType": "Digital",
		"Bindings": [
			{
				"Device": "Keyboard",
				"Input": "Q",
				"Event": "Trigger"
			},
{
				"Device": "Keyboard",
				"Input": "LeftArrow",
				"Event": "Trigger"
			},
			{
				"Device": "Controller",
				"Input": "Left",
				"Event": "Trigger"
			},
			{
				"Device": "Controller",
				"Input": "LeftShoulder",
				"Event": "Trigger"
			}
		]
	},
	"BulletChangeNext": {
		"InputType": "Digital",
		"Bindings": [
			{
				"Device": "Keyboard",
				"Input": "E",
				"Event": "Trigger"
			},
			{
				"Device": "Keyboard",
				"Input": "RightArrow",
				"Event": "Trigger"
			},
			{
				"Device": "Controller",
				"Input": "Right",
				"Event": "Trigger"
			},
			{
				"Device": "Controller",
				"Input": "RightShoulder",
				"Event": "Trigger"
			}
		]
	}
}